prospector2html/__init__.py
prospector2html/__main__.py
prospector2html/prospector2html.py
prospector2html-2.0.0.dist-info/LICENSE
prospector2html-2.0.0.dist-info/METADATA
prospector2html-2.0.0.dist-info/WHEEL
prospector2html-2.0.0.dist-info/entry_points.txt
prospector2html-2.0.0.dist-info/top_level.txt
prospector2html-2.0.0.dist-info/RECORD
