Metadata-Version: 2.1
Name: prospector2html
Version: 2.0.0
Summary: HTML report generator for prospector, semgrep, and GitLab SAST static analyzer tools.
Home-page: https://github.com/amdei/prospector-html
Author: amDei the Botan
Author-email: amdeich@gmail.com
Maintainer: Andrey Kulikov
Maintainer-email: amdeich@gmail.com
License: MIT
Keywords: prospector semgrep gitlab SAST static code analysis report pylint pyflakes pep8 mccabe frosted
Platform: any
Classifier: License :: OSI Approved :: MIT License
Classifier: Intended Audience :: Developers
Classifier: Environment :: Console
Classifier: Development Status :: 4 - Beta
Classifier: Operating System :: Unix
Classifier: Operating System :: POSIX :: Linux
Classifier: Operating System :: MacOS :: MacOS X
Classifier: Programming Language :: Python
Classifier: Programming Language :: Python :: 3
Classifier: Topic :: Utilities
Classifier: Topic :: Software Development :: Quality Assurance
License-File: LICENSE
Requires-Dist: PyYAML
Requires-Dist: json2html
